writefreely_to_markdown/__init__.py
writefreely_to_markdown/lib.py
writefreely_to_markdown/main.py
writefreely_to_markdown-0.2.0.dist-info/LICENSE
writefreely_to_markdown-0.2.0.dist-info/METADATA
writefreely_to_markdown-0.2.0.dist-info/WHEEL
writefreely_to_markdown-0.2.0.dist-info/entry_points.txt
writefreely_to_markdown-0.2.0.dist-info/RECORD
