Metadata-Version: 2.1
Name: writefreely-to-markdown
Version: 0.2.0
Summary: 
Home-page: https://github.com/rywng/writefreely-to-markdown
License: MIT
Keywords: blogging,blog,json,toml,markdown
Author: Ryan
Author-email: ryan@alien.gov
Requires-Python: >=3.12,<4.0
Classifier: License :: OSI Approved :: MIT License
Classifier: Programming Language :: Python :: 3
Classifier: Programming Language :: Python :: 3.12
Classifier: Programming Language :: Python :: 3.13
Requires-Dist: tomlkit (>=0.13.2,<0.14.0)
